Metadata-Version: 2.1
Name: hmin
Version: 0.0.3
Summary: Package for Clustering Text using Ko-BERT
Home-page: UNKNOWN
Author: Minsub Won
License: UNKNOWN
Platform: UNKNOWN
Requires-Python: >=3.6.0
